setup.py
invoice_crafter.egg-info/PKG-INFO
invoice_crafter.egg-info/SOURCES.txt
invoice_crafter.egg-info/dependency_links.txt
invoice_crafter.egg-info/requires.txt
invoice_crafter.egg-info/top_level.txt
invoicing/__init__.py
invoicing/invoice.py