Metadata-Version: 2.4
Name: invoice-crafter
Version: 1.0.0
Summary: This package converts Excel invoice files into PDF invoices. Simply provide an input and output directories, and also parameters to generate a PDF invoice for each file.
Home-page: https://github.com/Xannii
Author: Anna Balitska
Author-email: aa.llin.223@gmail.com
License: MIT
Keywords: invoice,excel,pdf,crafter
Classifier: Development Status :: 3 - Alpha
Classifier: Intended Audience :: Developers
Classifier: Topic :: Software Development :: Build Tools
Classifier: License :: OSI Approved :: MIT License
Classifier: Programming Language :: Python :: 3.8
Classifier: Programming Language :: Python :: 3.9
Classifier: Programming Language :: Python :: 3.10
Classifier: Programming Language :: Python :: 3.11
Requires-Dist: pandas
Requires-Dist: fpdf
Requires-Dist: openpyxl
Dynamic: author
Dynamic: author-email
Dynamic: classifier
Dynamic: home-page
Dynamic: keywords
Dynamic: license
Dynamic: requires-dist
Dynamic: summary
